divide_stuff/__init__.py
divide_stuff-0.1.1.dist-info/LICENSE
divide_stuff-0.1.1.dist-info/WHEEL
divide_stuff-0.1.1.dist-info/METADATA
divide_stuff-0.1.1.dist-info/RECORD
