Metadata-Version: 2.1
Name: divide-stuff
Version: 0.1.1
Summary: A very stupid project to learn about how to package apps for PyPy
Author: Thomas Steck
Author-email: thomas.steck@ingka.ikea.com
Requires-Python: >=3.8,<4.0
Classifier: Programming Language :: Python :: 3
Classifier: Programming Language :: Python :: 3.10
Classifier: Programming Language :: Python :: 3.8
Classifier: Programming Language :: Python :: 3.9
Requires-Dist: pprintpp (>=0.4.0,<0.5.0)
